basicauth/__init__.py
basicauth/basicauthutils.py
basicauth/compat.py
basicauth/decorators.py
basicauth/middleware.py
basicauth/response.py
django_basicauth-0.5.3.dist-info/AUTHORS.txt
django_basicauth-0.5.3.dist-info/LICENSE
django_basicauth-0.5.3.dist-info/METADATA
django_basicauth-0.5.3.dist-info/WHEEL
django_basicauth-0.5.3.dist-info/top_level.txt
django_basicauth-0.5.3.dist-info/RECORD
