Metadata-Version: 1.0
Name: django-basicauth
Version: 0.5.3
Summary: Basic auth utilities for Django.
Home-page: https://github.com/hirokiky/django-basicauth/
Author: Hiroki KIYOHARA
Author-email: hirokiky@gmail.com
License: MIT
Platform: UNKNOWN
